aioagi/__init__.py
aioagi/agi.py
aioagi/agi_writer.py
aioagi/app.py
aioagi/client.py
aioagi/client_exceptions.py
aioagi/client_proto.py
aioagi/client_reqrep.py
aioagi/commands.py
aioagi/connector.py
aioagi/exceptions.py
aioagi/hdrs.py
aioagi/helpers.py
aioagi/log.py
aioagi/parser.py
aioagi/protocol.py
aioagi/request.py
aioagi/response.py
aioagi/runner.py
aioagi/server.py
aioagi/urldispathcer.py
aioagi/ami/__init__.py
aioagi/ami/action.py
aioagi/ami/manager.py
aioagi/ami/message.py
aioagi/ami/parser.py
aioagi/ami/protocol.py
aioagi/ami/utils.py
aioagi_ik-1.3.0.dist-info/LICENSE.txt
aioagi_ik-1.3.0.dist-info/METADATA
aioagi_ik-1.3.0.dist-info/WHEEL
aioagi_ik-1.3.0.dist-info/top_level.txt
aioagi_ik-1.3.0.dist-info/RECORD
