Metadata-Version: 2.2
Name: aioagi-ik
Version: 1.3.0
Summary: Async agi client/server framework (asyncio)
Home-page: https://gitlab.com/VadimShakurov/aioagi.git
Author: Shakurov Vadim Vladimirovich
Author-email: apelsinsd@gmail.com
License: Apache License 2.0
Keywords: aiogi asyncio asterisk telephony voip
Classifier: License :: OSI Approved :: Apache Software License
Classifier: Intended Audience :: Developers
Classifier: Programming Language :: Python
Classifier: Programming Language :: Python :: 3.6
Classifier: Programming Language :: Python :: 3.7
Classifier: Programming Language :: Python :: 3.8
Classifier: Programming Language :: Python :: 3.12
Classifier: Operating System :: POSIX
Classifier: Operating System :: MacOS :: MacOS X
Classifier: Operating System :: Microsoft :: Windows
Classifier: Topic :: Communications :: Internet Phone
Classifier: Topic :: Communications :: Telephony
Classifier: Topic :: Software Development :: Libraries :: Python Modules
Classifier: Framework :: AsyncIO
License-File: LICENSE.txt
Requires-Dist: aiohttp<4,>=3.11
Requires-Dist: async_timeout<5,>=4.0
Provides-Extra: dev
Requires-Dist: ipdb; extra == "dev"
Requires-Dist: ipython; extra == "dev"
Provides-Extra: testing
Requires-Dist: coverage; extra == "testing"
Requires-Dist: pytest; extra == "testing"
Requires-Dist: pytest-asyncio; extra == "testing"
Requires-Dist: pytest-sugar; extra == "testing"
Requires-Dist: pytest-cov; extra == "testing"
Dynamic: author
Dynamic: author-email
Dynamic: classifier
Dynamic: description
Dynamic: description-content-type
Dynamic: home-page
Dynamic: keywords
Dynamic: license
Dynamic: provides-extra
Dynamic: requires-dist
Dynamic: summary
